blaubergvento_client/__init__.py
blaubergvento_client-1.0.0.dist-info/licenses/LICENSE
blaubergvento_client-1.0.0.dist-info/METADATA
blaubergvento_client-1.0.0.dist-info/WHEEL
blaubergvento_client-1.0.0.dist-info/top_level.txt
blaubergvento_client-1.0.0.dist-info/RECORD
