Metadata-Version: 2.4
Name: blaubergvento_client
Version: 1.0.0
Summary: A client for communicating with Blauberg vento (and derived) ventilators.
Home-page: https://github.com/michaelkrog/blaubergvento-python
Author: Michael Krog
Author-email: Michael Krog <info@apaq.dk>
License: MIT License
Project-URL: Homepage, https://github.com/michaelkrog/blaubergvento-python
Keywords: blauberg,duka,ventilator
Requires-Python: >=3.9
License-File: LICENSE
Provides-Extra: dev
Requires-Dist: black; extra == "dev"
Requires-Dist: bumpver; extra == "dev"
Requires-Dist: isort; extra == "dev"
Requires-Dist: pip-tools; extra == "dev"
Requires-Dist: pytest; extra == "dev"
Dynamic: author
Dynamic: home-page
Dynamic: license-file
